mrf/__init__.py
mrf/celestial.py
mrf/display.py
mrf/download.py
mrf/imtools.py
mrf/sbcontrast.py
mrf/task.py
mrf/utils.py
mrf/iraf/macosx/controlpar.par
mrf/iraf/macosx/ellipse.par
mrf/iraf/macosx/geompar.par
mrf/iraf/macosx/isoexam.par
mrf/iraf/macosx/magpar.par
mrf/iraf/macosx/map.par
mrf/iraf/macosx/model.par
mrf/iraf/macosx/samplepar.par
mrf/iraf/macosx/x_fitsio.e
mrf/iraf/macosx/x_images.e
mrf/iraf/macosx/x_isophote.e
mrf/iraf/macosx/x_tbplot.e
mrf/iraf/macosx/x_threed.e
mrf/iraf/macosx/x_ttools.e
mrf-1.0.4.dist-info/LICENSE
mrf-1.0.4.dist-info/METADATA
mrf-1.0.4.dist-info/WHEEL
mrf-1.0.4.dist-info/top_level.txt
mrf-1.0.4.dist-info/RECORD
