Metadata-Version: 2.1
Name: mrf
Version: 1.0.4
Summary: Multi-Resolution Filtering (MRF) is a method for isolating faint, extended emission in low-resolution images.
Home-page: https://github.com/AstroJacobLi/mrf
Author: Pieter van Dokkum, Jiaxuan Li
Author-email: pieter.vandokkum@yale.edu, jiaxuan_li@pku.edu.cn
License: MIT
Platform: UNKNOWN
Classifier: Development Status :: 4 - Beta
Classifier: License :: OSI Approved :: MIT License
Classifier: Intended Audience :: Science/Research
Classifier: Topic :: Scientific/Engineering :: Astronomy
Classifier: Operating System :: OS Independent
Classifier: Programming Language :: Python :: 2
Classifier: Programming Language :: Python :: 3
Classifier: Programming Language :: Python :: 3.6
Classifier: Programming Language :: Python :: 3.7
Requires-Python: >=2.7
Requires-Dist: numpy
Requires-Dist: scipy
Requires-Dist: astropy (>=3.2.1)
Requires-Dist: matplotlib (>=2.0)
Requires-Dist: sep
Requires-Dist: photutils
Requires-Dist: palettable
Requires-Dist: shapely
Requires-Dist: reproject (>=0.5.1)
Requires-Dist: tqdm
Requires-Dist: PyYAML
